aiadv/__init__.py
aiadv/_nbdev.py
aiadv/core.py
nbdev_template/__init__.py
nbdev_template/_nbdev.py
nbdev_template/core.py
aiadv-0.0.4.dist-info/LICENSE
aiadv-0.0.4.dist-info/METADATA
aiadv-0.0.4.dist-info/WHEEL
aiadv-0.0.4.dist-info/entry_points.txt
aiadv-0.0.4.dist-info/top_level.txt
aiadv-0.0.4.dist-info/RECORD
