Metadata-Version: 2.1
Name: aiadv
Version: 0.0.4
Summary: Python library, from AiAdventures, providing utility functions for downloading datasets, etc.
Home-page: https://github.com/ai-adventures/aiadv/tree/master/
Author: Ankur Singh
Author-email: as.ankursingh3.1@gmail.com
License: Apache Software License 2.0
Keywords: python
Platform: UNKNOWN
Classifier: Development Status :: 3 - Alpha
Classifier: Intended Audience :: Developers
Classifier: License :: OSI Approved :: Apache Software License
Classifier: Natural Language :: English
Classifier: Programming Language :: Python :: 3.6
Classifier: Programming Language :: Python :: 3.7
Classifier: Programming Language :: Python :: 3.8
Requires-Python: >=3.6
